optimux/__init__.py
optimux-1.0.0.dist-info/METADATA
optimux-1.0.0.dist-info/WHEEL
optimux-1.0.0.dist-info/top_level.txt
optimux-1.0.0.dist-info/RECORD
