Metadata-Version: 2.1
Name: optimux
Version: 1.0.0
Summary: A package
Home-page: https://github.com/yourusername/mypackage
Author: Example
Author-email: example@example.com
Classifier: Programming Language :: Python :: 3
Classifier: License :: OSI Approved :: MIT License
Classifier: Operating System :: OS Independent
Requires-Python: >=3
